plugin.cmake
setup.py
girder_curation/__init__.py
girder_curation.egg-info/PKG-INFO
girder_curation.egg-info/SOURCES.txt
girder_curation.egg-info/dependency_links.txt
girder_curation.egg-info/entry_points.txt
girder_curation.egg-info/not-zip-safe
girder_curation.egg-info/requires.txt
girder_curation.egg-info/top_level.txt
girder_curation/mail_templates/curation.approved.mako
girder_curation/mail_templates/curation.enabled.mako
girder_curation/mail_templates/curation.rejected.mako
girder_curation/mail_templates/curation.requested.mako
girder_curation/web_client/main.js
girder_curation/web_client/package.json
girder_curation/web_client/stylesheets/curationDialog.styl
girder_curation/web_client/templates/curationDialog.pug
girder_curation/web_client/templates/hierarchyWidgetCurationButton.pug
girder_curation/web_client/views/CurationDialog.js
girder_curation/web_client/views/HierarchyWidget.js
plugin_tests/__init__.py
plugin_tests/curationSpec.js
plugin_tests/curation_test.py